syntrend/__init__.py
syntrend/cli.py
syntrend/errors.py
syntrend/config/__init__.py
syntrend/config/model/__init__.py
syntrend/config/model/base_config.py
syntrend/config/model/constants.py
syntrend/config/model/document_tags.py
syntrend/config/model/enum.py
syntrend/config/model/module_config.py
syntrend/config/model/object_definition.py
syntrend/config/model/output_config.py
syntrend/config/model/project_config.py
syntrend/config/model/property_definition.py
syntrend/config/model/property_distribution.py
syntrend/config/parse/__init__.py
syntrend/config/parse/loader.py
syntrend/config/parse/parse_func.py
syntrend/config/parse/parser.py
syntrend/formatters/__init__.py
syntrend/formatters/ascii_table.py
syntrend/formatters/csv.py
syntrend/formatters/json.py
syntrend/formatters/sql.py
syntrend/formatters/xml.py
syntrend/generators/__base_types.py
syntrend/generators/__init__.py
syntrend/generators/choice.py
syntrend/generators/complex_object.py
syntrend/generators/datetime.py
syntrend/generators/float.py
syntrend/generators/integer.py
syntrend/generators/names.py
syntrend/generators/static.py
syntrend/generators/string.py
syntrend/generators/uuid.py
syntrend/utils/__init__.py
syntrend/utils/distributions.py
syntrend/utils/exc.py
syntrend/utils/filters.py
syntrend/utils/historian.py
syntrend/utils/manager.py
syntrend/utils/writers.py
syntrend-0.3.1.dist-info/METADATA
syntrend-0.3.1.dist-info/WHEEL
syntrend-0.3.1.dist-info/entry_points.txt
syntrend-0.3.1.dist-info/licenses/LICENSE
syntrend-0.3.1.dist-info/RECORD
