Metadata-Version: 2.4
Name: syntrend
Version: 0.3.1
Project-URL: Homepage, https://github.com/wsidl/syntrend
Project-URL: Repository, https://github.com/wsidl/syntrend
Project-URL: Issues, https://github.com/wsidl/syntrend/issues
Author-email: Will Siddall <will.siddall@gmail.com>
License-File: LICENSE
Classifier: Development Status :: 3 - Alpha
Classifier: Environment :: Console :: Curses
Classifier: Intended Audience :: Customer Service
Classifier: Intended Audience :: Developers
Classifier: Intended Audience :: Information Technology
Classifier: Intended Audience :: Science/Research
Classifier: Intended Audience :: System Administrators
Classifier: License :: OSI Approved :: GNU General Public License v3 (GPLv3)
Classifier: Operating System :: OS Independent
Classifier: Programming Language :: Python :: 3.11
Classifier: Topic :: Software Development :: Quality Assurance
Classifier: Topic :: Software Development :: Testing
Classifier: Topic :: Software Development :: Testing :: Traffic Generation
Requires-Python: <4,>=3.11
Requires-Dist: click
Requires-Dist: faker
Requires-Dist: jinja2
Requires-Dist: ruamel-yaml
Provides-Extra: test
Requires-Dist: pytest-cov>=5.0.0; extra == 'test'
Requires-Dist: pytest>=8.3.2; extra == 'test'
Requires-Dist: ruff>=0.9.6; extra == 'test'
